aliceplex/scrap/__init__.py
aliceplex/scrap/base.py
aliceplex/scrap/contsant.py
aliceplex/scrap/html.py
aliceplex/scrap/json.py
aliceplex/scrap/tvdb.py
aliceplex/scrap/utils.py
aliceplex/scrap/wiki.py
aliceplex_scrap-2.1.0.dist-info/LICENSE
aliceplex_scrap-2.1.0.dist-info/METADATA
aliceplex_scrap-2.1.0.dist-info/WHEEL
aliceplex_scrap-2.1.0.dist-info/top_level.txt
aliceplex_scrap-2.1.0.dist-info/RECORD
